Metadata-Version: 2.1
Name: thundersvm-cuda10
Version: 0.3.5
Summary: A Fast SVM Library on GPUs and CPUs
Home-page: https://github.com/Xtra-Computing/thundersvm
License: UNKNOWN
Platform: UNKNOWN
Classifier: Programming Language :: Python :: 3
Classifier: License :: OSI Approved :: Apache Software License
Requires-Python: >=3
